<annotation>
	<folder>Reem palm dataset</folder>
	<filename>image962.tif</filename>
	<path>D:\Google Drive\reaalali\Desktop\Reem palm dataset\image962.tif</path>
	<source>
		<database>Unknown</database>
	</source>
	<size>
		<width>256</width>
		<height>256</height>
		<depth>3</depth>
	</size>
	<segmented>0</segmented>
	<object>
		<name>palmtree</name>
		<pose>Unspecified</pose>
		<truncated>1</truncated>
		<difficult>0</difficult>
		<bndbox>
			<xmin>35</xmin>
			<ymin>1</ymin>
			<xmax>83</xmax>
			<ymax>27</ymax>
		</bndbox>
	</object>
	<object>
		<name>palmtree</name>
		<pose>Unspecified</pose>
		<truncated>1</truncated>
		<difficult>0</difficult>
		<bndbox>
			<xmin>1</xmin>
			<ymin>47</ymin>
			<xmax>26</xmax>
			<ymax>91</ymax>
		</bndbox>
	</object>
	<object>
		<name>palmtree</name>
		<pose>Unspecified</pose>
		<truncated>0</truncated>
		<difficult>0</difficult>
		<bndbox>
			<xmin>2</xmin>
			<ymin>100</ymin>
			<xmax>52</xmax>
			<ymax>151</ymax>
		</bndbox>
	</object>
	<object>
		<name>palmtree</name>
		<pose>Unspecified</pose>
		<truncated>0</truncated>
		<difficult>0</difficult>
		<bndbox>
			<xmin>10</xmin>
			<ymin>165</ymin>
			<xmax>60</xmax>
			<ymax>212</ymax>
		</bndbox>
	</object>
	<object>
		<name>palmtree</name>
		<pose>Unspecified</pose>
		<truncated>0</truncated>
		<difficult>0</difficult>
		<bndbox>
			<xmin>55</xmin>
			<ymin>199</ymin>
			<xmax>88</xmax>
			<ymax>244</ymax>
		</bndbox>
	</object>
	<object>
		<name>palmtree</name>
		<pose>Unspecified</pose>
		<truncated>0</truncated>
		<difficult>0</difficult>
		<bndbox>
			<xmin>19</xmin>
			<ymin>216</ymin>
			<xmax>54</xmax>
			<ymax>253</ymax>
		</bndbox>
	</object>
	<object>
		<name>palmtree</name>
		<pose>Unspecified</pose>
		<truncated>0</truncated>
		<difficult>0</difficult>
		<bndbox>
			<xmin>88</xmin>
			<ymin>148</ymin>
			<xmax>118</xmax>
			<ymax>176</ymax>
		</bndbox>
	</object>
	<object>
		<name>palmtree</name>
		<pose>Unspecified</pose>
		<truncated>0</truncated>
		<difficult>0</difficult>
		<bndbox>
			<xmin>93</xmin>
			<ymin>177</ymin>
			<xmax>125</xmax>
			<ymax>196</ymax>
		</bndbox>
	</object>
	<object>
		<name>palmtree</name>
		<pose>Unspecified</pose>
		<truncated>0</truncated>
		<difficult>0</difficult>
		<bndbox>
			<xmin>96</xmin>
			<ymin>198</ymin>
			<xmax>131</xmax>
			<ymax>218</ymax>
		</bndbox>
	</object>
	<object>
		<name>palmtree</name>
		<pose>Unspecified</pose>
		<truncated>0</truncated>
		<difficult>0</difficult>
		<bndbox>
			<xmin>105</xmin>
			<ymin>221</ymin>
			<xmax>143</xmax>
			<ymax>250</ymax>
		</bndbox>
	</object>
	<object>
		<name>palmtree</name>
		<pose>Unspecified</pose>
		<truncated>0</truncated>
		<difficult>0</difficult>
		<bndbox>
			<xmin>62</xmin>
			<ymin>88</ymin>
			<xmax>117</xmax>
			<ymax>139</ymax>
		</bndbox>
	</object>
	<object>
		<name>palmtree</name>
		<pose>Unspecified</pose>
		<truncated>0</truncated>
		<difficult>0</difficult>
		<bndbox>
			<xmin>48</xmin>
			<ymin>30</ymin>
			<xmax>102</xmax>
			<ymax>88</ymax>
		</bndbox>
	</object>
	<object>
		<name>palmtree</name>
		<pose>Unspecified</pose>
		<truncated>0</truncated>
		<difficult>0</difficult>
		<bndbox>
			<xmin>146</xmin>
			<ymin>71</ymin>
			<xmax>192</xmax>
			<ymax>117</ymax>
		</bndbox>
	</object>
	<object>
		<name>palmtree</name>
		<pose>Unspecified</pose>
		<truncated>0</truncated>
		<difficult>0</difficult>
		<bndbox>
			<xmin>122</xmin>
			<ymin>4</ymin>
			<xmax>193</xmax>
			<ymax>66</ymax>
		</bndbox>
	</object>
	<object>
		<name>palmtree</name>
		<pose>Unspecified</pose>
		<truncated>1</truncated>
		<difficult>0</difficult>
		<bndbox>
			<xmin>1</xmin>
			<ymin>1</ymin>
			<xmax>22</xmax>
			<ymax>47</ymax>
		</bndbox>
	</object>
</annotation>
